mcp_akshare/__init__.py
mcp_akshare/main.py
mcp_akshare_hust-0.1.1.dist-info/METADATA
mcp_akshare_hust-0.1.1.dist-info/WHEEL
mcp_akshare_hust-0.1.1.dist-info/entry_points.txt
mcp_akshare_hust-0.1.1.dist-info/RECORD
