Metadata-Version: 2.4
Name: mcp-akshare-hust
Version: 0.1.1
Summary: A Model Context Protocol server for AKShare stock data
Requires-Python: >=3.12
Requires-Dist: akshare>=1.16.76
Requires-Dist: bs4>=0.0.2
Requires-Dist: fastmcp>=2.0.0
Requires-Dist: pandas>=2.3.1
Requires-Dist: requests>=2.32.3
Requires-Dist: urllib3>=2.2.3
